preapp/__init__.py
preapp/__main__.py
preapp/hooks.py
preapp/node.py
preapp/question.py
preapp/assets/__init__.py
preapp/assets/nodejs.yml
preapp/assets/angular/__init__.py
preapp/assets/angular/karma.conf.js
preapp/assets/angular/nodejs.yml
preapp/assets/features/__init__.py
preapp/assets/features/accounts.json
preapp/assets/features/content.json
preapp/assets/features/data_management.json
preapp/assets/features/functionality.json
preapp/assets/features/geo_location.json
preapp/assets/features/payments.json
preapp/assets/github/__init__.py
preapp/assets/github/labels/__init__.py
preapp/assets/github/labels/pst.json
preapp/assets/python/__init__.py
preapp/assets/python/module/__init__.py
preapp/assets/python/module/__main__.py
preapp/assets/python/module/__test_util.py
preapp/assets/python/module/noxfile.py
preapp/assets/python/module/setup.py
preapp/assets/react/__init__.py
preapp/assets/react/nodejs.yml
preapp/assets/vue/__init__.py
preapp/assets/vue/nodejs.yml
preapp/nodes/__init__.py
preapp/nodes/framework_node.py
preapp/nodes/metadata_node.py
preapp/nodes/nodejs_node.py
preapp/nodes/output_node.py
preapp/nodes/platform_node.py
preapp/nodes/python_node.py
preapp/nodes/root_node.py
preapp/nodes/features/__init__.py
preapp/nodes/features/accounts_node.py
preapp/nodes/features/features_node.py
preapp/nodes/github/__init__.py
preapp/nodes/github/actions_node.py
preapp/nodes/github/clone.py
preapp/nodes/github/credentials_node.py
preapp/nodes/github/github_node.py
preapp/nodes/github/labels_node.py
preapp/nodes/github/repository_node.py
preapp/technologies/__init__.py
preapp/technologies/angular.py
preapp/technologies/python.py
preapp/technologies/react.py
preapp/technologies/vue.py
preapp/utils/__init__.py
preapp/utils/database.py
preapp/utils/fileio.py
preapp/utils/github.py
preapp/utils/miscellaneous.py
tests/__init__.py
tests/conftest.py
tests/credentials.json
tests/test_preapp.py
tests/web-config.json
preapp-0.0.3.dist-info/LICENSE
preapp-0.0.3.dist-info/METADATA
preapp-0.0.3.dist-info/WHEEL
preapp-0.0.3.dist-info/top_level.txt
preapp-0.0.3.dist-info/RECORD
