Metadata-Version: 2.1
Name: preapp
Version: 0.0.3
Summary: a tool that helps developers build github repositories from a design spec and backlog
Home-page: https://github.com/stephend017/preapp
Author: Stephen Davis
Author-email: stephenedavis17@gmail.com
License: MIT
Platform: UNKNOWN
Requires-Python: >=3.6
Requires-Dist: prompt-toolkit (==1.0.14)
Requires-Dist: Pygments (==2.6.1)
Requires-Dist: PyInquirer (==1.0.3)
Requires-Dist: regex (==2020.4.4)
Requires-Dist: six (==1.14.0)
Requires-Dist: wcwidth (==0.1.9)
Requires-Dist: PyGithub (==1.50)
Requires-Dist: automodinit (==0.16)
